Workbook

Sheet README
B2: Finance Planning — GenAI Prototype: Synthetic Stock Market Dataset
B3: Supporting data for: Banking / Finance-Planning GenAI hackathon problem statement
B5: Purpose
B6: This workbook supplies the 'stocks / market instruments' data referenced in the problem statement, to be combined with customer profile data (net worth, risk appetite, financial goals) so a GenAI model can generate 2-3 candidate finance plans per customer.
B8: Important
B9: All prices, returns, volatility, beta, P/E and dividend-yield figures are SYNTHETICALLY GENERATED (randomised within realistic ranges) for prototyping and demo purposes only. Company names, sectors and index membership are real for realism, but the numbers attached to them are NOT live market data and must never be used for actual investment advice.
B11: How to use
B12: 1) Stock_Master = investable universe tagged by risk band. 2) Index_Historical_Trends = 10-yr synthetic yearly returns per asset class, for 'past trend' based projections. 3) Risk_Category_Reference = maps a customer's risk appetite to an allocation style. 4) Sample_Financial_Plans = ready-made model portfolios (the '2-3 plans to choose from'). 5) Customer_Profile_Examples = worked examples showing profile -> plan mapping, the pattern your GenAI layer should replicate at run-time.
B14: Suggested GenAI flow
B15: Build customer profile -> classify risk score -> filter Stock_Master / Sample_Financial_Plans by risk band & goal horizon -> prompt the LLM with the filtered data + past trends -> LLM drafts 2-3 personalised plans with rationale -> customer selects one.
B18: Sheets: README | Stock_Master | Index_Historical_Trends | Risk_Category_Reference | Sample_Financial_Plans | Customer_Profile_Examples

Sheet Stock_Master
A1: Symbol | B1: Company Name | C1: Sector | D1: Market Cap Category | E1: Index Membership | F1: Risk Category | G1: Beta | H1: Current Price (INR) | I1: P/E Ratio | J1: Dividend Yield (%) | K1: 1Y Return (%) | L1: 3Y CAGR (%) | M1: 5Y CAGR (%) | N1: Volatility / Std Dev (%) | O1: Risk-Adjusted Return (3Y CAGR / Volatility)
A2: RELIANCE | B2: Reliance Industries | C2: Oil, Gas & Conglomerate | D2: Large Cap | E2: Nifty 50 | F2: Medium | G2: 0.89 | H2: 2634.19 | I2: 20.1 | J2: 0.45 | K2: -3.6 | L2: 18.8 | M2: 13.6 | N2: 23.9 | O2: =ROUND(L2/N2,2) -> 0.79
A3: TCS | B3: Tata Consultancy Services | C3: IT Services | D3: Large Cap | E3: Nifty 50 | F3: Low | G3: 0.56 | H3: 1108.96 | I3: 25.1 | J3: 0.87 | K3: 6 | L3: 13.8 | M3: 12.4 | N3: 13.8 | O3: =ROUND(L3/N3,2) -> 1
A4: HDFCBANK | B4: HDFC Bank | C4: Banking | D4: Large Cap | E4: Nifty 50 | F4: Medium | G4: 0.96 | H4: 3062.16 | I4: 37 | J4: 0.49 | K4: 10.2 | L4: 9.6 | M4: 9 | N4: 25.6 | O4: =ROUND(L4/N4,2) -> 0.38
A5: ICICIBANK | B5: ICICI Bank | C5: Banking | D5: Large Cap | E5: Nifty 50 | F5: Low | G5: 0.59 | H5: 657.85 | I5: 31.9 | J5: 2.43 | K5: 18.1 | L5: 14.8 | M5: 12.3 | N5: 19.8 | O5: =ROUND(L5/N5,2) -> 0.75
A6: INFY | B6: Infosys | C6: IT Services | D6: Large Cap | E6: Nifty 50 | F6: Low | G6: 0.58 | H6: 1384.76 | I6: 27.6 | J6: 3.19 | K6: 9.2 | L6: 8.3 | M6: 8.6 | N6: 17.3 | O6: =ROUND(L6/N6,2) -> 0.48
A7: HINDUNILVR | B7: Hindustan Unilever | C7: FMCG | D7: Large Cap | E7: Nifty 50 | F7: Low | G7: 0.94 | H7: 3464.68 | I7: 32.3 | J7: 1.83 | K7: 11.1 | L7: 16 | M7: 9.3 | N7: 14.8 | O7: =ROUND(L7/N7,2) -> 1.08
A8: ITC | B8: ITC Ltd | C8: FMCG | D8: Large Cap | E8: Nifty 50 | F8: Medium | G8: 0.96 | H8: 3287.79 | I8: 33.4 | J8: 1.3 | K8: -0.6 | L8: 18.6 | M8: 8.3 | N8: 21.8 | O8: =ROUND(L8/N8,2) -> 0.85
A9: SBIN | B9: State Bank of India | C9: Banking (PSU) | D9: Large Cap | E9: Nifty 50 | F9: Medium | G9: 1.13 | H9: 885.71 | I9: 22.7 | J9: 1.58 | K9: -5.6 | L9: 20.4 | M9: 17.3 | N9: 22 | O9: =ROUND(L9/N9,2) -> 0.93
A10: BHARTIARTL | B10: Bharti Airtel | C10: Telecom | D10: Large Cap | E10: Nifty 50 | F10: Low | G10: 0.63 | H10: 3788.77 | I10: 32.5 | J10: 1.65 | K10: 15.1 | L10: 10.7 | M10: 15.3 | N10: 15.7 | O10: =ROUND(L10/N10,2) -> 0.68
A11: KOTAKBANK | B11: Kotak Mahindra Bank | C11: Banking | D11: Large Cap | E11: Nifty 50 | F11: Low | G11: 0.61 | H11: 3056.46 | I11: 25.8 | J11: 2.82 | K11: 10.6 | L11: 13 | M11: 10.9 | N11: 20 | O11: =ROUND(L11/N11,2) -> 0.65
A12: LT | B12: Larsen & Toubro | C12: Capital Goods / Infra | D12: Large Cap | E12: Nifty 50 | F12: Low | G12: 0.75 | H12: 636.36 | I12: 15.9 | J12: 1.1 | K12: 14.5 | L12: 15.5 | M12: 11.4 | N12: 12.5 | O12: =ROUND(L12/N12,2) -> 1.24
A13: BAJFINANCE | B13: Bajaj Finance | C13: NBFC | D13: Large Cap | E13: Nifty 50 | F13: Low | G13: 0.79 | H13: 2031.78 | I13: 20 | J13: 2.29 | K13: 20.8 | L13: 14.2 | M13: 8.9 | N13: 19.1 | O13: =ROUND(L13/N13,2) -> 0.74
... A87: SADBHAV | B87: Sadbhav Engineering | C87: Infra (small cap, leveraged) | D87: Small Cap | E87: Nifty Smallcap 250 / Non-Index | F87: Very High | G87: 2.03 | H87: 446.62 | I87: 15.5 | J87: 0.17 | K87: 0 | L87: 28.6 | M87: 32.9 | N87: 46.9 | O87: =ROUND(L87/N87,2) -> 0.61
A89: Note: All figures above are synthetically generated for prototyping — not live market data. Company/sector/index-membership are illustrative real-world references.

Sheet Index_Historical_Trends
A1: Asset / Index | B1: 2016 | C1: 2017 | D1: 2018 | E1: 2019 | F1: 2020 | G1: 2021 | H1: 2022 | I1: 2023 | J1: 2024 | K1: 2025 | L1: 10Y Avg Return (%) | M1: 10Y Volatility (%)
A2: Nifty 50 | B2: 8.7 | C2: 1.4 | D2: 38.9 | E2: 3.7 | F2: -2.7 | G2: 7.9 | H2: 7.8 | I2: 25.2 | J2: 28 | K2: 10.2 | L2: =ROUND(AVERAGE(B2:K2),1) -> 12.9 | M2: =ROUND(STDEV(B2:K2),1) -> 13.3
A3: S&P BSE Sensex | B3: -31.5 | C3: 8.9 | D3: 2.7 | E3: -2.7 | F3: 4.7 | G3: 18 | H3: -3.3 | I3: 32.2 | J3: -4.9 | K3: -5 | L3: =ROUND(AVERAGE(B3:K3),1) -> 1.9 | M3: =ROUND(STDEV(B3:K3),1) -> 16.6
A4: Nifty Next 50 | B4: 20.5 | C4: 35.8 | D4: 31.4 | E4: 5.5 | F4: 11.1 | G4: 5.3 | H4: 38.3 | I4: 9.9 | J4: 14.7 | K4: 24.5 | L4: =ROUND(AVERAGE(B4:K4),1) -> 19.7 | M4: =ROUND(STDEV(B4:K4),1) -> 12.3
A5: Nifty Midcap 150 | B5: -9.5 | C5: 8.2 | D5: 74.2 | E5: 54.9 | F5: 37.9 | G5: 4.3 | H5: 47.7 | I5: 45 | J5: -17.9 | K5: 17.4 | L5: =ROUND(AVERAGE(B5:K5),1) -> 26.2 | M5: =ROUND(STDEV(B5:K5),1) -> 30.1
A6: Nifty Smallcap 250 | B6: -5.9 | C6: 16.7 | D6: 60.7 | E6: -54.4 | F6: 19.5 | G6: 55.9 | H6: -32.4 | I6: 63.2 | J6: -43.6 | K6: 14.8 | L6: =ROUND(AVERAGE(B6:K6),1) -> 9.5 | M6: =ROUND(STDEV(B6:K6),1) -> 43.1
A7: Nifty Bank | B7: 24.6 | C7: 1.9 | D7: 19.2 | E7: -6.1 | F7: 35.8 | G7: 4.4 | H7: 21 | I7: -0.7 | J7: 6 | K7: 39.4 | L7: =ROUND(AVERAGE(B7:K7),1) -> 14.6 | M7: =ROUND(STDEV(B7:K7),1) -> 15.7
A8: Nifty IT | B8: 42.8 | C8: 14.8 | D8: 32.8 | E8: 39 | F8: -2.1 | G8: 40.1 | H8: -10.5 | I8: 7.9 | J8: 8.2 | K8: 29 | L8: =ROUND(AVERAGE(B8:K8),1) -> 20.2 | M8: =ROUND(STDEV(B8:K8),1) -> 19
A9: Gold (INR) | B9: 4.9 | C9: -4.8 | D9: 12.1 | E9: 30.6 | F9: 29.1 | G9: 15.4 | H9: 3.9 | I9: -11.1 | J9: -3.4 | K9: 21.6 | L9: =ROUND(AVERAGE(B9:K9),1) -> 9.8 | M9: =ROUND(STDEV(B9:K9),1) -> 14.4
A10: Bank Fixed Deposit (avg) | B10: 7.2 | C10: 5 | D10: 6.3 | E10: 6.5 | F10: 5.7 | G10: 6.5 | H10: 7.3 | I10: 5.6 | J10: 5.8 | K10: 6.8 | L10: =ROUND(AVERAGE(B10:K10),1) -> 6.3 | M10: =ROUND(STDEV(B10:K10),1) -> 0.7
A11: 10Y Govt. Securities (G-Sec) | B11: 5.1 | C11: 7.5 | D11: 5.5 | E11: 7.9 | F11: 7.8 | G11: 8.1 | H11: 8.1 | I11: 6.8 | J11: 6.4 | K11: 5.4 | L11: =ROUND(AVERAGE(B11:K11),1) -> 6.9 | M11: =ROUND(STDEV(B11:K11),1) -> 1.2
A13: Note: Yearly figures are synthetically generated (randomised around a realistic mean/volatility per asset class) to illustrate 'past trend' inputs for plan generation — not actual historical index returns.

Sheet Risk_Category_Reference
A1: Risk Category | B1: Investor Profile | C1: Expected Annual Return Range (%) | D1: Expected Volatility Range (%) | E1: Suggested Equity Allocation (%) | F1: Suggested Debt/Gold Allocation (%) | G1: Typical Instruments | H1: Description
A2: Low | B2: Conservative | C2: 6 - 10 | D2: 10 - 15 | E2: 20 - 35 | F2: 65 - 80 | G2: Nifty 50 large-caps, Debt funds, FDs, G-Secs | H2: Capital preservation first; small equity sleeve for inflation-beating growth.
A3: Medium | B3: Moderate / Balanced | C3: 10 - 16 | D3: 16 - 24 | E3: 45 - 60 | F3: 40 - 55 | G3: Nifty 50 + select Nifty Next 50 / Midcap, Hybrid funds, Gold | H3: Balanced growth with manageable drawdowns; core-satellite equity approach.
A4: High | B4: Growth-Oriented | C4: 14 - 22 | D4: 24 - 34 | E4: 65 - 80 | F4: 20 - 35 | G4: Midcap & select Smallcap stocks, Sectoral/Thematic funds | H4: Higher equity tilt for long time-horizon investors comfortable with volatility.
A5: Very High | B5: Aggressive / Speculative | C5: 15 - 30+ (wide range, can be negative) | D5: 35 - 60+ | E5: 80 - 95 | F5: 5 - 20 | G5: Smallcap, turnaround/penny stocks, New-age tech, Thematic bets | H5: Maximum growth potential with high probability of sharp drawdowns; suited only for a small satellite allocation even for aggressive investors.

Sheet Sample_Financial_Plans
A1: Assumed Category Return / Volatility (editable inputs — used by formulas below)
A2: Asset Category | B2: Assumed Annual Return (%) | C2: Assumed Volatility (%)
A3: Large Cap Equity (Nifty 50) | B3: 12 | C3: 18
A4: Mid Cap Equity | B4: 15 | C4: 26
A5: Small Cap / High-Risk Equity | B5: 18 | C5: 38
A6: Debt / Fixed Income | B6: 7 | C6: 3
A7: Gold / Alternatives | B7: 8 | C7: 15
A10: Model Financial Plans (auto-computed from allocations above)
A11: Plan Name | B11: Target Investor Profile | C11: Large Cap Equity (%) | D11: Mid Cap Equity (%) | E11: Small/High-Risk Equity (%) | F11: Debt (%) | G11: Gold (%) | H11: Total (%) | I11: Expected Portfolio Return (%) | J11: Approx. Portfolio Volatility (%)
A12: Plan A — Capital Shield | B12: Conservative (Low Risk) | C12: 30 | D12: 10 | E12: 0 | F12: 50 | G12: 10 | H12: 100 | I12: =ROUND((C12*$B$3+D12*$B$4+E12*$B$5+F12*$B$6+G12*$B$7)/100,2) -> 9.4 | J12: =ROUND((C12*$C$3+D12*$C$4+E12*$C$5+F12*$C$6+G12*$C$7)/100,2) -> 11
A13: Plan B — Steady Growth | B13: Moderate / Balanced | C13: 35 | D13: 20 | E13: 10 | F13: 25 | G13: 10 | H13: 100 | I13: =ROUND((C13*$B$3+D13*$B$4+E13*$B$5+F13*$B$6+G13*$B$7)/100,2) -> 11.55 | J13: =ROUND((C13*$C$3+D13*$C$4+E13*$C$5+F13*$C$6+G13*$C$7)/100,2) -> 17.55
A14: Plan C — Wealth Builder | B14: Growth-Oriented (High Risk) | C14: 30 | D14: 30 | E14: 25 | F14: 10 | G14: 5 | H14: 100 | I14: =ROUND((C14*$B$3+D14*$B$4+E14*$B$5+F14*$B$6+G14*$B$7)/100,2) -> 13.7 | J14: =ROUND((C14*$C$3+D14*$C$4+E14*$C$5+F14*$C$6+G14*$C$7)/100,2) -> 23.75
A15: Plan D — Max Momentum | B15: Aggressive (Very High Risk) | C15: 20 | D15: 30 | E15: 40 | F15: 5 | G15: 5 | H15: 100 | I15: =ROUND((C15*$B$3+D15*$B$4+E15*$B$5+F15*$B$6+G15*$B$7)/100,2) -> 14.85 | J15: =ROUND((C15*$C$3+D15*$C$4+E15*$C$5+F15*$C$6+G15*$C$7)/100,2) -> 27.5
A17: Note: 'Approx. Portfolio Volatility' is a simplified weighted-average (ignores cross-asset correlation) for demo purposes — a production model should use a full covariance-based portfolio-risk calculation.

Sheet Customer_Profile_Examples
A1: Customer ID | B1: Name | C1: Age | D1: Net Worth (INR) | E1: Risk Appetite | F1: Primary Financial Goal | G1: Time Horizon (yrs) | H1: Monthly Investment Capacity (INR) | I1: Recommended Plan | J1: Recommended Plan Expected Return (%) | K1: Alternate Plan (Option 2)
A2: CUST001 | B2: Ramesh Iyer | C2: 58 | D2: 12500000 | E2: Low | F2: Retirement Income | G2: 5 | H2: 30000 | I2: Plan A — Capital Shield | J2: =ROUND(INDEX(Sample_Financial_Plans!$I$12:$I$15,MATCH(I2,Sample_Financial_Plans!$A$12:$A$15,0)),2) -> 9.4 | K2: Plan B — Steady Growth
A3: CUST002 | B3: Anita Sharma | C3: 34 | D3: 4200000 | E3: Medium | F3: Child's Education (2038) | G3: 12 | H3: 45000 | I3: Plan B — Steady Growth | J3: =ROUND(INDEX(Sample_Financial_Plans!$I$12:$I$15,MATCH(I3,Sample_Financial_Plans!$A$12:$A$15,0)),2) -> 11.55 | K3: Plan C — Wealth Builder
A4: CUST003 | B4: Vikram Rao | C4: 29 | D4: 950000 | E4: High | F4: Wealth Creation / Early FIRE | G4: 20 | H4: 25000 | I4: Plan C — Wealth Builder | J4: =ROUND(INDEX(Sample_Financial_Plans!$I$12:$I$15,MATCH(I4,Sample_Financial_Plans!$A$12:$A$15,0)),2) -> 13.7 | K4: Plan D — Max Momentum
A5: CUST004 | B5: Sneha Kapoor | C5: 26 | D5: 300000 | E5: Very High | F5: Aggressive Wealth Growth | G5: 25 | H5: 15000 | I5: Plan D — Max Momentum | J5: =ROUND(INDEX(Sample_Financial_Plans!$I$12:$I$15,MATCH(I5,Sample_Financial_Plans!$A$12:$A$15,0)),2) -> 14.85 | K5: Plan C — Wealth Builder
A6: CUST005 | B6: Deepak Menon | C6: 45 | D6: 8000000 | E6: Medium | F6: Home Down-payment (2029) | G6: 3 | H6: 60000 | I6: Plan B — Steady Growth | J6: =ROUND(INDEX(Sample_Financial_Plans!$I$12:$I$15,MATCH(I6,Sample_Financial_Plans!$A$12:$A$15,0)),2) -> 11.55 | K6: Plan A — Capital Shield
A8: Note: These 5 customers are illustrative examples of how a built customer profile (net worth + risk appetite + goal/horizon) maps to a recommended model plan, plus one alternate — mirroring the 'couple of plans to choose from' requirement. A GenAI layer would replace this static mapping with a dynamically generated, personalised rationale per customer.
